CHANGELOG
COPYRIGHT
LICENSE
MANIFEST.in
README
setup.py
doc/Makefile
doc/conf.py
doc/index.rst
sphinxcontrib/__init__.py
sphinxcontrib/inheritance.py
sphinxcontrib/.ropeproject/config.py
sphinxcontrib_inheritance.egg-info/PKG-INFO
sphinxcontrib_inheritance.egg-info/SOURCES.txt
sphinxcontrib_inheritance.egg-info/dependency_links.txt
sphinxcontrib_inheritance.egg-info/namespace_packages.txt
sphinxcontrib_inheritance.egg-info/not-zip-safe
sphinxcontrib_inheritance.egg-info/requires.txt
sphinxcontrib_inheritance.egg-info/top_level.txt
test/conf.py
test/index.rst
test/submodule1/index.rst
test/submodule2/index.rst