Metadata-Version: 1.1
Name: sphinxcontrib-inheritance
Version: 0.7.1
Summary: Documentation inheritance functionality for Sphinx
Home-page: https://bitbucket.org/nantic/sphinxcontrib-inheritance
Author: NaN·tic
Author-email: info@nan-tic.com
License: BSD
Download-URL: http://pypi.python.org/pypi/sphinxcontrib-inheritance
Platform: any
Classifier: Development Status :: 3 - Alpha
Classifier: Environment :: Console
Classifier: Environment :: Web Environment
Classifier: Intended Audience :: Developers
Classifier: License :: OSI Approved :: BSD License
Classifier: Operating System :: OS Independent
Classifier: Programming Language :: Python
Classifier: Topic :: Documentation
Classifier: Topic :: Utilities
